<?xml version="1.0" encoding="UTF-8"?>

<!DOCTYPE mapper
        PUBLIC "-//mybatis.org//DTD Mapper 3.0//EN"
        "http://mybatis.org/dtd/mybatis-3-mapper.dtd">

<mapper namespace="com.web.LoginModule.dao.ChatDao">

<!--    <resultMap id="peopleMap" type="com.web.LoginModule.entity.tx_people" >-->
<!--        <id column="pid" property="pid" jdbcType="VARCHAR" />-->
<!--        <result column="pname" property="pname" jdbcType="VARCHAR" />-->
<!--        <result column="pstate" property="pstate" jdbcType="VARCHAR" />-->
<!--    </resultMap>-->

<!--    <resultMap id="groupMap" type="com.web.LoginModule.entity.tx_group" >-->
<!--        <id column="gid" property="gid" jdbcType="VARCHAR" />-->
<!--        <result column="gname" property="gname" jdbcType="VARCHAR" />-->
<!--    </resultMap>-->

    <resultMap id="msgMap" type="com.web.LoginModule.entity.tx_msg" >
        <id column="msgid" property="msgid" jdbcType="VARCHAR" />
        <result column="msgContent" property="msgContent" jdbcType="VARCHAR" />
        <result column="groupId" property="groupId" jdbcType="VARCHAR" />
        <result column="fromId" property="fromId" jdbcType="VARCHAR" />
        <result column="fromName" property="fromName" jdbcType="VARCHAR" />
        <result column="toId" property="toId" jdbcType="VARCHAR" />
        <result column="toName" property="toName" jdbcType="VARCHAR" />
        <result column="msgType" property="msgType" jdbcType="VARCHAR" />
        <result column="addTime" property="addTime" jdbcType="DATE" />
    </resultMap>

<!--    <resultMap id="grouppeopleMap" type="com.web.LoginModule.entity.tx_group_people" >-->
<!--        <id column="mid" property="mid" jdbcType="VARCHAR" />-->
<!--        <result column="content" property="content" jdbcType="VARCHAR" />-->
<!--        <result column="gid" property="gid" jdbcType="VARCHAR" />-->
<!--        <result column="pid" property="pid" jdbcType="VARCHAR" />-->
<!--        <result column="msgtype" property="msgtype" jdbcType="VARCHAR" />-->
<!--    </resultMap>-->

    <!-- 查询当前用户和其他人的聊天记录 -->
    <select id="selectRecordsById" resultMap="msgMap" parameterType="com.web.LoginModule.entity.tx_msg">
        select * from (select * from tx_msg where fromName = #{fromName} and toName = #{toName}
        union all
        select * from tx_msg where fromName = #{toName} and toName = #{fromName}) record
        order by record.addTime
    </select>

    <!-- 查询当前用户和其他人的聊天记录 -->
    <select id="selectById" resultMap="msgMap" parameterType="com.web.LoginModule.entity.tx_msg">
        select * from tx_msg where fromName = #{fromName} and toName = #{toName} order by addTime;
    </select>


    <insert id="addMsg" parameterType="com.web.LoginModule.entity.tx_msg" >
        insert into tx_msg
        values(
            #{msgid,jdbcType=VARCHAR},
            #{msgContent,jdbcType=VARCHAR},
            #{groupId,jdbcType=VARCHAR},
            #{fromId,jdbcType=VARCHAR},
            #{fromName,jdbcType=VARCHAR},
            #{toId,jdbcType=VARCHAR},
            #{toName,jdbcType=VARCHAR},
            #{msgType,jdbcType=VARCHAR},
            #{addTime,jdbcType=VARCHAR}
        )
    </insert>





</mapper>